{"docs_bunpou_course10_1-11-9.md":"0nfqFX0a","docs_term_flexibleuse.md":"BZKBiGMP","docs_bunpou_course1_1-2-2.md":"4vzBNO5R","docs_term_1-9-1.md":"CNJNqWks","docs_term_lyx.md":"Cc6vX5YE","docs_term_ty.md":"BEAcrHZH","docs_term_yy.md":"BEOvGsLa","docs_bunpou_course1_1-2-1.md":"DhY7qcRo","docs_bunpou_course10_1-11-6.md":"ComGgA8N","docs_auxiliary_te.md":"WOT61shG","docs_term_ltc.md":"BX5Bti9n","docs_bunpou_course10_1-11-7.md":"BvxxsvRW","docs_term_1-8-1.md":"AovUa8pm","docs_bunpou_course10_1-11-8.md":"Trvf9mn3","docs_bunpou_course10_1-11-1.md":"D7s070HE","docs_bunpou_course10_1-11-10.md":"DUOQ-0gP","index.md":"DyU6RBJX","docs_auxiliary_he.md":"Ba9pCbzU","docs_term_1-5-4.md":"BSi-mKxP","docs_bunpou_course10_1-11-11.md":"DB0nbIFL","docs_auxiliary_to.md":"zrUl-CYB","docs_bunpou_course3_1-4-1.md":"Ch9QNRMT","docs_term_1-6-1.md":"C60rf3_p","docs_bunpou_course10_1-11-12.md":"BXt7frrA","docs_bunpou_course10_1-11-4.md":"B1IPomDj","docs_bunpou_course3_1-4-10.md":"F_N1lZcI","docs_auxiliary_mo.md":"Fh4LwPJk","docs_bunpou_course10_1-11-3.md":"DGeG7Ebc","docs_auxiliary_ha.md":"DFgpPOsb","docs_bunpou_course5_1-6-4.md":"DeKdU3-N","docs_verb.md":"BBKwTKGx","docs_bunpou_course10_1-11-5.md":"nskHoSaW","docs_bunpou_course6_1-7-14.md":"C0_O9lKD","docs_auxiliary_no.md":"BRzBu9o7","docs_adjective.md":"DSMf7Ob3","docs_bunpou_course11_1-12-03.md":"BwHkv7Ld","docs_term_ltform.md":"CtB6-kDt","docs_bunpou_course6_1-7-2.md":"zTQBj_rd","docs_bunpou_course11_1-12-04.md":"BSa8e7FB","docs_bunpou_course5_1-6-2.md":"DLtUeyOV","docs_bunpou_course6_1-7-3.md":"DRUSZTlS","docs_auxiliary_ka.md":"BMKiIYgV","docs_bunpou_course4_1-5-2.md":"C3wRzFqd","docs_bunpou_course10_1-11-2.md":"DcAhEpA2","docs_bunpou_course10_1-11-13.md":"CIR4R9u5","docs_bunpou_course5_1-6-3.md":"CsDfJYz2","docs_bunpou_course2_1-3-8.md":"CadOmVsT","docs_term_interrogative.md":"B3H7SIo4","docs_bunpou_course8_1-9-4.md":"lij9V_NU","docs_auxiliary_ni.md":"58AEkxQ_","docs_bunpou_course7_1-8-9.md":"BO0tCh6J","docs_bunpou_course11_1-12-02.md":"knDdk9Lh","docs_bunpou_course11_1-12-05.md":"XVxeUOQl","docs_bunpou_course11_1-12-06.md":"D8nbKnVB","docs_bunpou_course11_1-12-07.md":"XjYJ9MqX","docs_bunpou_course11_1-12-01.md":"U9Xpe7Gm","docs_bunpou_course11_1-12-08.md":"D_r6Je0X","docs_bunpou_course2_1-3-1.md":"vb71GWK7","docs_bunpou_course2_1-3-2.md":"D4AF4Y10","docs_bunpou_course11_1-12-09.md":"Bv3s8V5_","docs_bunpou_course2_1-3-3.md":"CyXr16aj","docs_bunpou_course11_1-12-10.md":"DeImWUhR","docs_auxiliary_ne.md":"BxP7g_sh","docs_bunpou_course2_1-3-4.md":"Dn6GwqYR","docs_bunpou_course2_1-3-5.md":"BuI8HMzk","docs_auxiliary_wo.md":"B0OyECgi","docs_bunpou_course8_1-9-3.md":"C0XSlTjv","docs_bunpou_course8_1-9-2.md":"BoAZNuyf","docs_bunpou_course9_1-10-1.md":"1VoMZZWx","docs_bunpou_course8_1-9-10.md":"BfUv8yXP","docs_bunpou_course8_1-9-5.md":"D1I78bfB","docs_bunpou_course8_1-9-11.md":"WUEDDNzy","docs_bunpou_course8_1-9-6.md":"DzSTQlr3","docs_bunpou_course8_1-9-7.md":"BtVmpllI","docs_bunpou_course8_1-9-12.md":"2xiFNJvh","docs_bunpou_course8_1-9-13.md":"db7IqSee","docs_bunpou_course8_1-9-8.md":"D2Rfab_b","docs_bunpou_course9_1-10-5.md":"N8LKQApg","docs_bunpou_course9_1-10-6.md":"BKroWwAo","docs_bunpou_course9_1-10-7.md":"7j_nJA8k","docs_bunpou_course9_1-10-8.md":"BSG_dFMO","docs_bunpou_course9_1-10-3.md":"DMCFVSEQ","docs_bunpou_course8_1-9-1.md":"T9zdXG8H","docs_bunpou_course8_1-9-9.md":"IIIof_Sy","docs_bunpou_course9_1-10-10.md":"4pjceTgK","docs_bunpou_course9_1-10-11.md":"CrgDB6Bl","docs_bunpou_course9_1-10-2.md":"Bw8vAKXC","docs_bunpou_course9_1-10-12.md":"Cb6F9Cve","docs_bunpou_course9_1-10-13.md":"D0PM4afL","docs_bunpou_course9_1-10-4.md":"BdfadLyL","docs_bunpou_course6_1-7-6.md":"BoM_qpRm","docs_bunpou_course2_1-3-6.md":"CC8a1eMz","docs_bunpou_course6_1-7-5.md":"Dxyq6ULH","docs_term_1-5-2.md":"VMjHv_dB","docs_bunpou_course2_1-3-7.md":"mreIRmf2","docs_bunpou_course3_1-4-11.md":"CV21M1NA","docs_bunpou_course3_1-4-2.md":"C6pPrDwg","docs_bunpou_course3_1-4-3.md":"fNMnQKhF","docs_bunpou_course3_1-4-5.md":"DPeiFMf_","docs_bunpou_course3_1-4-4.md":"BUJm7W8L","docs_bunpou_course3_1-4-6.md":"Bigbvg0O","docs_bunpou_course6_1-7-7.md":"B6aylCP7","docs_bunpou_course9_1-10-9.md":"C6eeh5Uj","docs_bunpou_course6_1-7-4.md":"B7brKNjO","docs_index.md":"Ci2Qqd5h","docs_term_1-11-1.md":"DQHc6uvT","docs_bunpou_course3_1-4-7.md":"BVSK4LQE","docs_term_1-5-5.md":"DaQ4dXmX","docs_bunpou_course6_1-7-12.md":"NSQe8uVe","docs_bunpou_course7_1-8-1.md":"flCFTpwd","docs_bunpou_course6_1-7-1.md":"DQ1z7AcW","docs_bunpou_course5_1-6-6.md":"CfYIBNil","docs_bunpou_course6_1-7-13.md":"RzLo8C-8","docs_bunpou_course4_1-5-3.md":"B9YMmxsM","docs_bunpou_course6_1-7-10.md":"DisnP0Kq","docs_bunpou_course6_1-7-11.md":"fzAjGPfy","docs_bunpou_course7_1-8-4.md":"DrGktF9p","docs_bunpou_course5_1-6-5.md":"nn-H9R-b","docs_bunpou_course6_1-7-9.md":"BzPIQVjx","docs_term_1-4-2.md":"Dkh7nh-z","docs_bunpou_course6_1-7-8.md":"IHKU-nEO","docs_directions.md":"CPstROOs","docs_kosoado.md":"CRkLNGh4","docs_bunpou_course7_1-8-6.md":"DskzUVnR","docs_bunpou_course7_1-8-7.md":"DmU6t245","docs_term_1-4-1.md":"Cz2ayl28","docs_bunpou_course5_1-6-1.md":"DZUHM7QL","docs_term_1-5-1.md":"BYuXnZex","docs_bunpou_course7_1-8-3.md":"CPXrmpL2","docs_bunpou_course7_1-8-5.md":"BKWgtZd0","docs_bunpou_course3_1-4-8.md":"Bh_lCY05","docs_bunpou_course3_1-4-9.md":"BXGz4XA0","docs_bunpou_course7_1-8-2.md":"Ck7AoBut","docs_term_1-4-3.md":"D4Tf7fUI","docs_bunpou_course7_1-8-8.md":"DwDcnHPB","docs_term_1-5-3.md":"DhlcMnw2","readme.md":"B0-shJFS","docs_bunpou_course4_1-5-1.md":"CDZ_Gz1I"}
